{
  "title": "65th_Annual_Grammy_Awards",
  "url": "https://en.wikipedia.org/wiki/65th_Annual_Grammy_Awards",
  "summary": "The 65th Annual Grammy Awards ceremony was held at the Crypto.com Arena in Los Angeles on February 5, 2023. It recognized the best recordings, compositions, and artists of the eligibility year \u2013 October 1, 2021 to September 30, 2022 \u2013 as determined by the members of National Academy of Recording Arts and Sciences. The nominations were announced on November 15, 2022. South African comedian Trevor Noah, who hosted the 63rd and 64th ceremonies, returned again.Beyonc\u00e9 received the most nominations (nine) and tied Maverick City Music for wins (four), followed by Kendrick Lamar with eight nominations and three wins, and Adele and Brandi Carlile with seven nominations each. With a career total of 88 nominations, Beyonc\u00e9 tied with her husband Jay-Z as the most nominated artists in Grammy history. Bad Bunny's Un Verano Sin Ti (2022) became the first Spanish-language album to be nominated for Album of the Year.With her win in the Best Dance/Electronic Album category, Beyonc\u00e9 passed Hungarian-British conductor Georg Solti for the record of most Grammy awards in the ceremony's history, with 32. Harry Styles won Album of the Year for Harry's House, becoming the first male British solo artist to win since George Michael in 1989. Lizzo won Record of the Year for \"About Damn Time\", becoming the first black woman to win the award since Whitney Houston in 1994. Bonnie Raitt won Song of the Year for \"Just Like That\", becoming the first female solo songwriter to win since Amy Winehouse in 2008.\nWith her win in the Best Audio Book, Narration & Storytelling Recording category, Viola Davis became the 18th person to win Emmy, Grammy, Oscar, and Tony awards in their entertainment career.",
  "content": [
    {
      "section_title": "Background",
      "section_content": [
        {
          "sentence": "For the 2023 ceremony, the academy announced several changes for different categories and eligibility rules:",
          "refs": [
            "https://www.grammy.com/news/2023-grammys-new-categories-songwriter-year-best-video-game-soundtrack-social-impact-special-merit-award-65th-grammy-awards"
          ]
        }
      ],
      "subsections": [
        {
          "section_title": "Category changes",
          "section_content": [],
          "subsections": []
        },
        {
          "section_title": "Album eligibility",
          "section_content": [],
          "subsections": []
        },
        {
          "section_title": "Craft committees",
          "section_content": [],
          "subsections": []
        }
      ]
    },
    {
      "section_title": "Performers",
      "section_content": [],
      "subsections": [
        {
          "section_title": "Premiere ceremony",
          "section_content": [
            {
              "sentence": "The performers for the ceremony were announced on January 29, 2023",
              "refs": []
            }
          ],
          "subsections": []
        },
        {
          "section_title": "Main ceremony",
          "section_content": [
            {
              "sentence": "The first wave of performers for the ceremony were announced on January 25, 2023, with Harry Styles confirmed a few days later",
              "refs": []
            },
            {
              "sentence": "Performers for the In Memoriam segment were announced on February 1, 2023",
              "refs": [
                "https://www.grammy.com/news/2023-grammys-performers-first-wave-announced-performances",
                "https://www.grammy.com/news/harry-styles-performance--2023-grammys-announcement"
              ]
            },
            {
              "sentence": "The 50 Years of Hip Hop performance was announced on February 3",
              "refs": [
                "https://www.hollywoodreporter.com/news/music-news/grammys-2023-in-memoriam-migos-takeoff-loretta-lynn-1235315435/"
              ]
            }
          ],
          "subsections": []
        }
      ]
    },
    {
      "section_title": "Presenters",
      "section_content": [],
      "subsections": []
    },
    {
      "section_title": "Winners and nominees",
      "section_content": [
        {
          "sentence": "The following are the winners and nominees of the 65th annual Grammy Awards",
          "refs": []
        },
        {
          "sentence": "Winners appear first and highlighted in bold.",
          "refs": [
            "https://www.grammy.com/news/2023-grammy-nominations-complete-winners-nominees-list"
          ]
        }
      ],
      "subsections": [
        {
          "section_title": "General field",
          "section_content": [
            {
              "sentence": "Record of the Year",
              "refs": []
            },
            {
              "sentence": "Album of the Year",
              "refs": []
            },
            {
              "sentence": "Song of the Year",
              "refs": []
            },
            {
              "sentence": "Best New Artist",
              "refs": []
            }
          ],
          "subsections": []
        },
        {
          "section_title": "Pop",
          "section_content": [
            {
              "sentence": "Best Pop Solo Performance",
              "refs": []
            },
            {
              "sentence": "Best Pop Duo/Group Performance",
              "refs": []
            },
            {
              "sentence": "Best Traditional Pop Vocal Album",
              "refs": []
            },
            {
              "sentence": "Best Pop Vocal Album",
              "refs": []
            }
          ],
          "subsections": []
        },
        {
          "section_title": "Dance/Electronic",
          "section_content": [
            {
              "sentence": "Best Dance/Electronic Recording",
              "refs": []
            },
            {
              "sentence": "Best Dance/Electronic Album",
              "refs": []
            }
          ],
          "subsections": []
        },
        {
          "section_title": "Contemporary instrumental",
          "section_content": [
            {
              "sentence": "Best Contemporary Instrumental Album",
              "refs": []
            }
          ],
          "subsections": []
        },
        {
          "section_title": "Rock",
          "section_content": [
            {
              "sentence": "Best Rock Performance",
              "refs": []
            },
            {
              "sentence": "Best Metal Performance",
              "refs": []
            },
            {
              "sentence": "Best Rock Song",
              "refs": []
            },
            {
              "sentence": "Best Rock Album",
              "refs": []
            }
          ],
          "subsections": []
        },
        {
          "section_title": "Alternative",
          "section_content": [
            {
              "sentence": "Best Alternative Music Performance",
              "refs": []
            },
            {
              "sentence": "Best Alternative Music Album",
              "refs": []
            }
          ],
          "subsections": []
        },
        {
          "section_title": "R&B",
          "section_content": [
            {
              "sentence": "Best R&B Performance",
              "refs": []
            },
            {
              "sentence": "Best Traditional R&B Performance",
              "refs": []
            },
            {
              "sentence": "Best R&B Song",
              "refs": []
            },
            {
              "sentence": "Best Progressive R&B Album",
              "refs": []
            },
            {
              "sentence": "Best R&B Album",
              "refs": []
            }
          ],
          "subsections": []
        },
        {
          "section_title": "Rap",
          "section_content": [
            {
              "sentence": "Best Rap Performance",
              "refs": []
            },
            {
              "sentence": "Best Melodic Rap Performance",
              "refs": []
            },
            {
              "sentence": "Best Rap Song",
              "refs": []
            },
            {
              "sentence": "Best Rap Album",
              "refs": []
            }
          ],
          "subsections": []
        },
        {
          "section_title": "Country",
          "section_content": [
            {
              "sentence": "Best Country Solo Performance",
              "refs": []
            },
            {
              "sentence": "Best Country Duo/Group Performance",
              "refs": []
            },
            {
              "sentence": "Best Country Song",
              "refs": []
            },
            {
              "sentence": "Best Country Album",
              "refs": []
            }
          ],
          "subsections": []
        },
        {
          "section_title": "New Age",
          "section_content": [
            {
              "sentence": "Best New Age, Ambient or Chant Album",
              "refs": []
            }
          ],
          "subsections": []
        },
        {
          "section_title": "Jazz",
          "section_content": [
            {
              "sentence": "Best Improvised Jazz Solo",
              "refs": []
            },
            {
              "sentence": "Best Jazz Vocal Album",
              "refs": []
            },
            {
              "sentence": "Best Jazz Instrumental Album",
              "refs": []
            },
            {
              "sentence": "Best Large Jazz Ensemble Album",
              "refs": []
            },
            {
              "sentence": "Best Latin Jazz Album",
              "refs": []
            }
          ],
          "subsections": []
        },
        {
          "section_title": "Gospel/contemporary Christian",
          "section_content": [
            {
              "sentence": "Best Gospel Performance/Song",
              "refs": []
            },
            {
              "sentence": "Best Contemporary Christian Music Performance/Song",
              "refs": []
            },
            {
              "sentence": "Best Gospel Album",
              "refs": []
            },
            {
              "sentence": "Best Contemporary Christian Music Album",
              "refs": []
            },
            {
              "sentence": "Best Roots Gospel Album",
              "refs": []
            }
          ],
          "subsections": []
        },
        {
          "section_title": "Latin",
          "section_content": [
            {
              "sentence": "Best Latin Pop Album",
              "refs": []
            },
            {
              "sentence": "Best M\u00fasica Urbana Album",
              "refs": []
            },
            {
              "sentence": "Best Latin Rock or Alternative Album",
              "refs": []
            },
            {
              "sentence": "Best Regional Mexican Music Album (Including Tejano)",
              "refs": []
            },
            {
              "sentence": "Best Tropical Latin Album",
              "refs": []
            }
          ],
          "subsections": []
        },
        {
          "section_title": "American roots",
          "section_content": [
            {
              "sentence": "Best American Roots Performance",
              "refs": []
            },
            {
              "sentence": "Best Americana Performance",
              "refs": []
            },
            {
              "sentence": "Best American Roots Song",
              "refs": []
            },
            {
              "sentence": "Best Americana Album",
              "refs": []
            },
            {
              "sentence": "Best Bluegrass Album",
              "refs": []
            },
            {
              "sentence": "Best Traditional Blues Album",
              "refs": []
            },
            {
              "sentence": "Best Contemporary Blues Album",
              "refs": []
            },
            {
              "sentence": "Best Folk Album",
              "refs": []
            },
            {
              "sentence": "Best Regional Roots Music Album",
              "refs": []
            }
          ],
          "subsections": []
        },
        {
          "section_title": "Reggae",
          "section_content": [
            {
              "sentence": "Best Reggae Album",
              "refs": []
            }
          ],
          "subsections": []
        },
        {
          "section_title": "Global",
          "section_content": [
            {
              "sentence": "Best Global Music Performance",
              "refs": []
            },
            {
              "sentence": "Best Global Music Album",
              "refs": []
            }
          ],
          "subsections": []
        },
        {
          "section_title": "Children's",
          "section_content": [
            {
              "sentence": "Best Children's Album",
              "refs": []
            }
          ],
          "subsections": []
        },
        {
          "section_title": "Spoken word",
          "section_content": [
            {
              "sentence": "Best Audio Book, Narration\u00a0& Storytelling Recording",
              "refs": []
            },
            {
              "sentence": "Best Spoken Word Poetry Album",
              "refs": []
            }
          ],
          "subsections": []
        },
        {
          "section_title": "Comedy",
          "section_content": [
            {
              "sentence": "Best Comedy Album",
              "refs": []
            }
          ],
          "subsections": []
        },
        {
          "section_title": "Musical theater",
          "section_content": [
            {
              "sentence": "Best Musical Theater Album",
              "refs": []
            }
          ],
          "subsections": []
        },
        {
          "section_title": "Visual media",
          "section_content": [
            {
              "sentence": "Best Compilation Soundtrack for Visual Media",
              "refs": []
            },
            {
              "sentence": "Best Score Soundtrack for Visual Media",
              "refs": []
            },
            {
              "sentence": "Best Score Soundtrack for Video Games and Other Interactive Media",
              "refs": []
            },
            {
              "sentence": "Best Song Written for Visual Media",
              "refs": []
            }
          ],
          "subsections": []
        },
        {
          "section_title": "Composition and arrangement",
          "section_content": [
            {
              "sentence": "Best Instrumental Composition",
              "refs": []
            },
            {
              "sentence": "Best Arrangement, Instrumental or A Cappella",
              "refs": []
            },
            {
              "sentence": "Best Arrangement, Instruments and Vocals",
              "refs": []
            }
          ],
          "subsections": []
        },
        {
          "section_title": "Package, notes and historical",
          "section_content": [
            {
              "sentence": "Best Recording Package",
              "refs": []
            },
            {
              "sentence": "Best Boxed or Special Limited Edition Package",
              "refs": []
            },
            {
              "sentence": "Best Album Notes",
              "refs": []
            },
            {
              "sentence": "Best Historical Album",
              "refs": []
            }
          ],
          "subsections": []
        },
        {
          "section_title": "Production",
          "section_content": [
            {
              "sentence": "Best Engineered Album, Non-Classical",
              "refs": []
            },
            {
              "sentence": "Producer of the Year, Non-Classical",
              "refs": []
            },
            {
              "sentence": "Best Remixed Recording, Non-Classical",
              "refs": []
            },
            {
              "sentence": "Best Immersive Audio Album",
              "refs": []
            },
            {
              "sentence": "Best Engineered Album, Classical",
              "refs": []
            },
            {
              "sentence": "Producer of the Year, Classical",
              "refs": []
            }
          ],
          "subsections": []
        },
        {
          "section_title": "Songwriting",
          "section_content": [
            {
              "sentence": "Songwriter of the Year, Non-ClassicalPerformers names appear in parentheses.",
              "refs": []
            }
          ],
          "subsections": []
        },
        {
          "section_title": "Classical",
          "section_content": [
            {
              "sentence": "Best Orchestral Performance",
              "refs": []
            },
            {
              "sentence": "Best Opera Recording",
              "refs": []
            },
            {
              "sentence": "Best Choral Performance",
              "refs": []
            },
            {
              "sentence": "Best Chamber Music/Small Ensemble Performance",
              "refs": []
            },
            {
              "sentence": "Best Classical Instrumental Solo",
              "refs": []
            },
            {
              "sentence": "Best Classical Solo Vocal Album",
              "refs": []
            },
            {
              "sentence": "Best Classical Compendium",
              "refs": []
            },
            {
              "sentence": "Best Contemporary Classical Composition",
              "refs": []
            }
          ],
          "subsections": []
        },
        {
          "section_title": "Music video and film",
          "section_content": [
            {
              "sentence": "Best Music Video",
              "refs": []
            },
            {
              "sentence": "Best Music Film",
              "refs": []
            }
          ],
          "subsections": []
        }
      ]
    },
    {
      "section_title": "Special merit awards",
      "section_content": [],
      "subsections": [
        {
          "section_title": "MusiCares Person of the Year",
          "section_content": [],
          "subsections": []
        },
        {
          "section_title": "Lifetime Achievement Awards",
          "section_content": [],
          "subsections": []
        },
        {
          "section_title": "Dr. Dre Global Impact Award",
          "section_content": [],
          "subsections": []
        },
        {
          "section_title": "Best Song for Social Change",
          "section_content": [],
          "subsections": []
        }
      ]
    },
    {
      "section_title": "Multiple nominations and awards",
      "section_content": [
        {
          "sentence": "The following received multiple nominations:",
          "refs": []
        },
        {
          "sentence": "Three:",
          "refs": []
        },
        {
          "sentence": "Two:",
          "refs": []
        },
        {
          "sentence": "The following received multiple awards:",
          "refs": []
        }
      ],
      "subsections": []
    },
    {
      "section_title": "In memoriam",
      "section_content": [
        {
          "sentence": "The show honored artists and industry professionals who had died within the last year",
          "refs": []
        }
      ],
      "subsections": []
    },
    {
      "section_title": "References",
      "section_content": [],
      "subsections": []
    },
    {
      "section_title": "External links",
      "section_content": [],
      "subsections": []
    }
  ],
  "references": {
    "1": "https://tvline.com/2023/02/06/grammys-ratings-2023-cbs-viewership/",
    "2": "https://www.grammy.com/news/2023-grammys-air-date-nominations-announced-65th-grammy-awards",
    "3": "https://www.grammy.com/news/2023-grammy-nominations-complete-winners-nominees-list",
    "4": "https://variety.com/2022/music/news/trevor-noah-returns-grammy-awards-host-1235462201/",
    "5": "https://www.theguardian.com/music/live/2023/feb/05/grammys-2023-harry-styles-bad-bunny-beyonce-adele-taylor-swift",
    "6": "https://www.nme.com/news/music/grammys-nominations-2023-beyonce-kendrick-lamar-adele-and-harry-styles-score-the-most-nods-3349585",
    "7": "https://www.nbcnews.com/news/nbcblk/beyonce-ties-jay-z-nominated-artists-grammy-awards-history-rcna57334",
    "8": "https://www.cnn.com/2022/11/15/entertainment/bad-bunny-album-grammy-nomination/index.html",
    "9": "https://apnews.com/article/2023-grammys-show-0a4bad7a27caf90868621973a504f40d",
    "10": "https://pitchfork.com/news/viola-davis-achieves-egot-with-best-audiobook-win-at-2023-grammys/",
    "11": "https://www.grammy.com/news/2023-grammys-new-categories-songwriter-year-best-video-game-soundtrack-social-impact-special-merit-award-65th-grammy-awards",
    "12": "https://www.grammy.com/news/2023-grammys-award-premiere-ceremony-performers-presenters-carlos-vives-samara-joy-madison-cunningham-arooj-aftab",
    "13": "https://www.grammy.com/news/2023-grammys-performers-first-wave-announced-performances",
    "14": "https://www.grammy.com/news/harry-styles-performance--2023-grammys-announcement",
    "15": "https://www.hollywoodreporter.com/news/music-news/grammys-2023-in-memoriam-migos-takeoff-loretta-lynn-1235315435/",
    "16": "https://www.cbsnews.com/newyork/news/2023-grammys-hip-hop-celebration/",
    "17": "https://www.usatoday.com/story/entertainment/music/2023/02/05/grammy-awards-2023-live-updates/11170771002/",
    "18": "https://pitchfork.com/live/grammys-2023-live-updates/?id=63e076a28239cbf4436a5f77",
    "19": "https://www.grammy.com/news/2023-grammy-nominations-complete-winners-nominees-list",
    "20": "https://pitchfork.com/live/grammys-2023-live-updates/?id=63e07dacad6f7fe56e183fdb",
    "21": "https://pitchfork.com/news/kacey-musgraves-and-migos-quavo-lead-2023-grammys-in-memoriam-tribute/",
    "22": "https://www.rollingstone.com/music/music-news/takeoff-christine-mcvie-loretta-lynn-2023-grammys-tribute-watch-1234669210/"
  },
  "spicy_entities": {
    "65th_annual_grammy_awards": "CARDINAL",
    "65th": "ORDINAL",
    "annual grammy awards": "EVENT",
    "the crypto.com arena": "FAC",
    "los angeles": "GPE",
    "february 5, 2023": "DATE",
    "the eligibility year": "DATE",
    "october 1, 2021 to september 30, 2022": "DATE",
    "national academy of recording arts and sciences": "ORG",
    "november 15, 2022": "DATE",
    "south african": "NORP",
    "trevor noah": "PERSON",
    "63rd": "ORDINAL",
    "64th": "ORDINAL",
    "nine": "CARDINAL",
    "maverick city music": "FAC",
    "four": "CARDINAL",
    "kendrick lamar": "PERSON",
    "eight": "CARDINAL",
    "three": "CARDINAL",
    "adele": "PERSON",
    "brandi carlile": "ORG",
    "seven": "CARDINAL",
    "88": "CARDINAL",
    "beyonc\u00e9": "NORP",
    "jay-z": "PERSON",
    "grammy": "PERSON",
    "bad bunny's": "PERSON",
    "un verano": "FAC",
    "2022": "DATE",
    "first": "ORDINAL",
    "spanish": "LANGUAGE",
    "album": "GPE",
    "the best dance/electronic album": "ORG",
    "hungarian": "NORP",
    "british": "NORP",
    "georg solti": "PERSON",
    "32": "CARDINAL",
    "harry styles": "PERSON",
    "harry": "PERSON",
    "house": "ORG",
    "george michael": "PERSON",
    "1989": "DATE",
    "lizzo won record": "PERSON",
    "about damn time": "WORK_OF_ART",
    "whitney houston": "PERSON",
    "1994": "DATE",
    "bonnie raitt": "PERSON",
    "just like that": "WORK_OF_ART",
    "amy winehouse": "PERSON",
    "2008": "DATE",
    "narration & storytelling recording": "ORG",
    "davis": "PERSON",
    "18th": "ORDINAL",
    "oscar": "PERSON",
    "tony": "PERSON",
    "2023": "DATE",
    "january 29, 2023": "DATE",
    "january 25, 2023": "DATE",
    "a few days later": "DATE",
    "memoriam": "NORP",
    "february 1,": "DATE",
    "the 50 years of": "DATE",
    "hip hop": "GPE",
    "february 3": "DATE",
    "annual": "DATE",
    "grammy awards": "EVENT",
    "the year": "DATE",
    "duo/group performance": "ORG",
    "best traditional pop vocal album": "ORG",
    "dance/electronic": "ORG",
    "best traditional r&b performance": "ORG",
    "best rap song": "PERSON",
    "best country duo/group performance": "ORG",
    "best country song": "PERSON",
    "best jazz vocal album": "PERSON",
    "best jazz instrumental album": "PERSON",
    "best large jazz ensemble album": "ORG",
    "latin": "NORP",
    "gospel": "PERSON",
    "christian": "NORP",
    "best contemporary christian music performance/song": "ORG",
    "best gospel album": "PERSON",
    "best roots gospel album": "PERSON",
    "m\u00fasica": "GPE",
    "urbana album": "PERSON",
    "latin rock": "LOC",
    "best regional mexican music album (including tejano": "ORG",
    "american": "NORP",
    "best american roots performance": "WORK_OF_ART",
    "best bluegrass album": "PERSON",
    "best traditional blues album": "PERSON",
    "best regional roots music album": "ORG",
    "reggae": "ORG",
    "best reggae album": "ORG",
    "global music album": "ORG",
    "spoken": "PERSON",
    "best comedy album": "WORK_OF_ART",
    "best musical theater album": "WORK_OF_ART",
    "best song written": "PERSON",
    "package": "WORK_OF_ART",
    "best recording package": "WORK_OF_ART",
    "non-classical": "ORG",
    "best remixed recording": "PERSON",
    "classical": "ORG",
    "non-classicalperformers": "ORG",
    "best opera recording": "ORG",
    "contemporary classical composition": "ORG",
    "best music video": "WORK_OF_ART",
    "best music film": "ORG",
    "two": "CARDINAL",
    "the last year": "DATE"
  },
  "flair_entities": [
    "los angeles",
    "trevor noah",
    "best m\u00fasica urbana album",
    "whitney houston",
    "georg solti",
    "american",
    "reggae  best reggae album",
    "harry's house",
    "about damn time",
    "brandi carlile",
    "christian  best gospel performance",
    "viola davis",
    "south african",
    "just like that",
    "record of the year",
    "american roots song",
    "hungarian-british",
    "george michael",
    "classical",
    "best regional mexican music album",
    "in memoriam",
    "tony awards",
    "oscar",
    "song of the year",
    "65th annual grammy awards",
    "album of the year.with",
    "bonnie raitt",
    "maverick city music",
    "grammy awards",
    "national academy of recording arts and sciences",
    "jay-z",
    "album of the year",
    "a cappella",
    "beyonc\u00e9",
    "harry styles",
    "emmy, grammy",
    "grammy",
    "kendrick lamar",
    "lizzo",
    "crypto.com arena",
    "adele",
    "bad bunny's un verano sin ti",
    "amy winehouse",
    "latin  best latin pop album",
    "british",
    "spanish-language"
  ]
}